optillm/__init__.py
optillm/batching.py
optillm/bon.py
optillm/conversation_logger.py
optillm/cot_decoding.py
optillm/cot_reflection.py
optillm/entropy_decoding.py
optillm/inference.py
optillm/leap.py
optillm/litellm_wrapper.py
optillm/mcts.py
optillm/moa.py
optillm/plansearch.py
optillm/pvg.py
optillm/reread.py
optillm/rstar.py
optillm/rto.py
optillm/self_consistency.py
optillm/server.py
optillm/thinkdeeper.py
optillm/thinkdeeper_mlx.py
optillm/z3_solver.py
optillm/autothink/__init__.py
optillm/autothink/autothink.py
optillm/autothink/classifier.py
optillm/autothink/example.py
optillm/autothink/processor.py
optillm/autothink/steering.py
optillm/cepo/__init__.py
optillm/cepo/cepo.py
optillm/cepo/configs/cepo_config.yaml
optillm/cepo/configs/cepo_config_gptoss.yaml
optillm/cepo/configs/cepo_config_qwen3.yaml
optillm/deepconf/__init__.py
optillm/deepconf/confidence.py
optillm/deepconf/deepconf.py
optillm/deepconf/processor.py
optillm/mars/__init__.py
optillm/mars/agent.py
optillm/mars/aggregator.py
optillm/mars/answer_extraction.py
optillm/mars/mars.py
optillm/mars/prompts.py
optillm/mars/strategy_network.py
optillm/mars/verifier.py
optillm/mars/workspace.py
optillm/plugins/coc_plugin.py
optillm/plugins/deep_research_plugin.py
optillm/plugins/deepthink_plugin.py
optillm/plugins/executecode_plugin.py
optillm/plugins/genselect_plugin.py
optillm/plugins/json_plugin.py
optillm/plugins/longcepo_plugin.py
optillm/plugins/majority_voting_plugin.py
optillm/plugins/mcp_plugin.py
optillm/plugins/memory_plugin.py
optillm/plugins/privacy_plugin.py
optillm/plugins/proxy_plugin.py
optillm/plugins/readurls_plugin.py
optillm/plugins/router_plugin.py
optillm/plugins/spl_plugin.py
optillm/plugins/web_search_plugin.py
optillm/plugins/deep_research/__init__.py
optillm/plugins/deep_research/research_engine.py
optillm/plugins/deep_research/session_state.py
optillm/plugins/deepthink/__init__.py
optillm/plugins/deepthink/reasoning_modules.py
optillm/plugins/deepthink/self_discover.py
optillm-0.3.12.dist-info/licenses/LICENSE
optillm-0.3.12.dist-info/METADATA
optillm-0.3.12.dist-info/WHEEL
optillm-0.3.12.dist-info/entry_points.txt
optillm-0.3.12.dist-info/top_level.txt
optillm-0.3.12.dist-info/RECORD
