Metadata-Version: 2.4
Name: optillm
Version: 0.3.12
Summary: An optimizing inference proxy for LLMs.
Author-email: codelion <codelion@okyasoft.com>
License-Expression: Apache-2.0
Project-URL: Homepage, https://github.com/codelion/optillm
Project-URL: Repository, https://github.com/codelion/optillm
Project-URL: Issues, https://github.com/codelion/optillm/issues
Classifier: Programming Language :: Python :: 3
Classifier: Operating System :: OS Independent
Requires-Python: >=3.10
License-File: LICENSE
Requires-Dist: numpy
Requires-Dist: networkx
Requires-Dist: openai
Requires-Dist: z3-solver
Requires-Dist: aiohttp
Requires-Dist: flask
Requires-Dist: torch
Requires-Dist: transformers
Requires-Dist: azure-identity
Requires-Dist: tiktoken
Requires-Dist: scikit-learn
Requires-Dist: litellm
Requires-Dist: google-cloud-aiplatform
Requires-Dist: requests
Requires-Dist: beautifulsoup4
Requires-Dist: lxml
Requires-Dist: presidio_analyzer
Requires-Dist: presidio_anonymizer
Requires-Dist: nbconvert
Requires-Dist: nbformat
Requires-Dist: ipython
Requires-Dist: ipykernel
Requires-Dist: peft
Requires-Dist: bitsandbytes
Requires-Dist: gradio<5.16.0
Requires-Dist: spacy<3.8.0
Requires-Dist: cerebras_cloud_sdk
Requires-Dist: outlines[transformers]
Requires-Dist: sentencepiece
Requires-Dist: mcp
Requires-Dist: adaptive-classifier
Requires-Dist: datasets
Requires-Dist: PyYAML
Requires-Dist: selenium
Requires-Dist: webdriver-manager
Requires-Dist: mlx-lm>=0.24.0; platform_machine == "arm64" and sys_platform == "darwin"
Provides-Extra: eval
Requires-Dist: tabulate; extra == "eval"
Requires-Dist: accelerate; extra == "eval"
Requires-Dist: huggingface_hub; extra == "eval"
Requires-Dist: httpx; extra == "eval"
Requires-Dist: tqdm; extra == "eval"
Requires-Dist: pandas; extra == "eval"
Dynamic: license-file
